imageedit/__init__.py
imageedit/effects.py
imageedit/imagegrab.py
imageedit/imagetracer.py
imageedit/io.py
imageedit/resources/FiraCode-Light.ttf
imageedit/transform.py
imageedit-2023.dist-info/LICENSE.md
imageedit-2023.dist-info/METADATA
imageedit-2023.dist-info/WHEEL
imageedit-2023.dist-info/RECORD
