Metadata-Version: 2.1
Name: imageedit
Version: 2023
Summary: Create various icon masks and shading effects with the imageedit library
Home-page: https://github.com/FredHappyface/Python.ImageEdit
License: MIT
Author: FredHappyface
Requires-Python: >=3.8,<4.0
Classifier: Development Status :: 5 - Production/Stable
Classifier: Intended Audience :: Developers
Classifier: Intended Audience :: Education
Classifier: License :: OSI Approved :: MIT License
Classifier: Natural Language :: English
Classifier: Operating System :: OS Independent
Classifier: Programming Language :: Python :: 3
Classifier: Programming Language :: Python :: 3.8
Classifier: Programming Language :: Python :: 3.9
Classifier: Programming Language :: Python :: 3.10
Classifier: Programming Language :: Python :: 3.11
Classifier: Programming Language :: Python :: Implementation :: CPython
Classifier: Topic :: Multimedia :: Graphics
Classifier: Topic :: Software Development :: Libraries :: Python Modules
Classifier: Topic :: Utilities
Requires-Dist: Pillow (>=9.1.0,<10)
Requires-Dist: blendmodes (>=2022,<2024)
Requires-Dist: colourswatch (>=2022.0.1,<2024)
Requires-Dist: install-playwright (>=0.0.0,<2)
Requires-Dist: layeredimage (>=2022.0.1,<2024)
Requires-Dist: playwright (>=1.29.1,<2)
Requires-Dist: svgtrace (>=2022,<2024)
Project-URL: Documentation, https://github.com/FredHappyface/Python.ImageEdit/blob/master/README.md
Project-URL: Repository, https://github.com/FredHappyface/Python.ImageEdit
